jakluz_de21/__init__.py
jakluz_de21/data_transformations.py
jakluz_de21-0.1.0.dist-info/METADATA
jakluz_de21-0.1.0.dist-info/WHEEL
jakluz_de21-0.1.0.dist-info/RECORD
