Metadata-Version: 2.1
Name: jakluz-de21
Version: 0.1.0
Summary: A set of functions that are very handy for data analysis.
Author: Jakub Kluz
Author-email: j.kluz@zoho.com
Requires-Python: >=3.11,<4.0
Classifier: Programming Language :: Python :: 3
Classifier: Programming Language :: Python :: 3.11
Requires-Dist: numpy (>=1.25.2,<2.0.0)
